Metadata-Version: 2.1
Name: iso4
Version: 0.0.2
Summary: ISO 4 abbreviation of publication titles in Python.
Home-page: https://github.com/adlpr/iso4
Author: Alex DelPriore
Author-email: delpriore@stanford.edu
License: UNKNOWN
Platform: UNKNOWN
Classifier: Programming Language :: Python :: 3
Classifier: License :: OSI Approved :: MIT License
Classifier: Operating System :: OS Independent
Requires-Python: >=3.6
